Workbook

Sheet RESUMEN 2022-2
D1: SEDE | E1: FACULTAD | F1: PROGRAMA | G1: NÚMERO DE PRACTICAS
G2: TEORICO | H2: TEORICO PRACTICO | I2: PRACTICO | J2: PRACTICA PEDAGOGICA | K2: TOTAL POR FACULTAD | M2: FACULTAD | N2: Total
A3: CARACTER DE LOS CURSOS CON SOLICITUD PRÁCTICAS EXTRAMUROS | D3: NEIVA | E3: EDUCACIÓN | F3: LICENCIATURA EN EDUCACIÓN ARTÍSTICA | H3: 3 | K3: 45 | M3: EDUCACIÓN | N3: =K3 -> 45
A4: TEORICO | B4: =G26 -> 30 | D4: NEIVA | M4: CIENCIAS SOCIALES Y HUMANAS | N4: =K12 -> 15
A5: TEORICO PRACTICO | B5: =H26 -> 181 | D5: NEIVA | F5: LICENCIATURA EN EDUCACIÓN INFANTIL | G5: 1 | M5: CIENCIAS JURIDICAS Y POLITICAS | N5: =K16 -> 2
A6: PRACTICO | B6: 1 | D6: NEIVA | F6: LICENCIATURA EN CIENCIAS NATURALES Y EDUCACIÓN AMBIENTAL | G6: 9 | H6: 7 | M6: INGENIERIA | N6: =K17 -> 125
A7: PRACTICA PEDAGOGICA | B7: 1 | D7: NEIVA | F7: LICENCIATURA EN CIENCIAS SOCIALES | H7: 4 | M7: CIENCIAS EXACTAS Y NATURALES | N7: =K25 -> 26
B8: =SUM(B4:B7) -> 213 | D8: NEIVA | F8: LICENCIATURA EN MATEMATICAS | G8: 1 | H8: 7 | M8: ECONOMÍA Y ADMINISTRACIÓN | N8: 0
D9: NEIVA | F9: LICENCIATURA EN LITERATURA Y LENGUA CASTELLANA | J9: 1 | M9: SALUD | N9: 0
D10: NEIVA | F10: LICENCIATURA EN EDUCACIÓN FISICA, RECREACIÓN Y DEPORTES | H10: 5 | M10: TOTALES | N10: 213
D11: NEIVA | F11: DEPARTAMENTO DE PSICOPEDAGOGIA | G11: 5 | H11: 2
D12: NEIVA | E12: CIENCIAS SOCIALES Y HUMANAS | F12: ANTROPOLOGIA | H12: 5 | K12: 15
D13: PITALITO | F13: COMUNICACIÓN SOCIAL Y PERIODISMO | G13: 1 | H13: 1
D14: NEIVA | F14: COMUNICACIÓN SOCIAL Y PERIODISMO | G14: 2 | H14: 4
D15: NEIVA | F15: PSICOLOGÍA | G15: 1 | H15: 1
D16: NEIVA | E16: CIENCIAS JURIDICAS Y POLITICAS | F16: CIENCIA POLITICA | G16: 2 | K16: =G16 -> 2
D17: NEIVA | E17: INGENIERIA | F17: INGENIERÍA AGROINDUSTRIAL | H17: 9 | K17: 125
D18: GARZÓN | F18: INGENIERÍA AGRÍCOLA | G18: 3 | H18: 29 | I18: 1
D19: LA PLATA | F19: INGENIERÍA AGRÍCOLA | H19: 30
D20: PITALITO | F20: INGENIERÍA AGRÍCOLA | G20: 2 | H20: 16
D21: NEIVA | F21: INGENIERÍA AGRÍCOLA | G21: 2 | H21: 19
D22: NEIVA | F22: INGENIERÍA ELECTRÓNICA | H22: 1
D23: NEIVA | F23: INGENIERÍA CIVIL | G23: 1 | H23: 5
D24: NEIVA | F24: INGENIERÍA DE PETROLEOS | H24: 7
D25: NEIVA | E25: CIENCIAS EXACTAS Y NATURALES | F25: BIOLOGIA APLICADA | H25: 26 | K25: 26
F26: TOTALES | G26: =SUM(G3:G25) -> 30 | H26: =SUM(H3:H25) -> 181 | I26: =SUM(I3:I25) -> 1 | J26: =SUM(J3:J25) -> 1 | K26: =SUM(K3:K25) -> 213
B31: Nota: | C31: 7 Eliminadas por ajuste del programa de Lic Ciencias Naturales y Educación Ambiental
C32: Eliminación del número de días de las prácticas del Programa de Lic en Educación Física, Recreación y Deportes
C35: No. de solicitudes | D35: COMBUSTIBLE | E35: PEAJES | F35: PARQUEADERO | G35: IMPREVISTOS | H35: VALOR BUS EXTERNO | I35: COSTO TOTAL DÍAS VIATICOS DOCENTES | J35: TOTAL
A36: CONSOLIDADO | C36: 213 | D36: $22.730.000 | E36: $11.515.000 | F36: $2.815.000 | G36: 0 | H36: $481.370.000 | I36: $73.729.514 | J36: $592.159.514
A37: TEORICO-PRACTICO | C37: 162 | D37: $20.880.000 | E37: $10.783.000 | F37: $2.620.000 | G37: 0 | H37: $382.240.000 | I37: $62.569.514 | J37: $479.092.514
A38: TEORICO | C38: 29 | D38: $1.850.000 | E38: $732.000 | F38: $195.000 | G38: 0 | H38: $80.920.000 | I38: $9.000.000 | J38: $92.697.000
A39: GRANJA EXPERIMENTAL TODAS LAS SEDES | C39: 22 | D39: 0 | E39: 0 | F39: 0 | G39: 0 | H39: $18.210.000 | I39: $960.000 | J39: $19.170.000 | K39: Aprobadas en Consejo Académico
A42: AJUSTADO | C42: No. de solicitudes | D42: COMBUSTIBLE | E42: PEAJES | F42: PARQUEADERO | G42: IMPREVISTOS | H42: VALOR BUS EXTERNO | I42: COSTO TOTAL DÍAS VIATICOS DOCENTES | J42: TOTAL
C43: 161 | D43: ='TEORICO - PRACTICOS'!P162 -> 20490000 | E43: ='TEORICO - PRACTICOS'!Q162 -> 10174000 | F43: ='TEORICO - PRACTICOS'!R162 -> 2440000 | G43: ='TEORICO - PRACTICOS'!S162 -> 0 | H43: ='TEORICO - PRACTICOS'!T162 -> 350385000 | I43: ='TEORICO - PRACTICOS'!V162 -> 60836362 | J43: ='TEORICO - PRACTICOS'!W162 -> 444325362 | K43: =592159514-J43-19170000 -> 128664152 | L43: Reducción con los ajustes realizados
B47: TRAZABILIDAD
A49: 1. | B49: Mediante Circular de Programación No. 022 del 23 de mayo de 2022, se establecio como fecha limite el 5 de agosto para la remisión de las solicitudes de practicas extramuros con previa aval de los Consejos de Facultad
A50: 2. | B50: El 29 de agosto de 2022 mediante correo electrónico se envio a las Secretarías Académicas de las diferentes Facultad el consolidado de las prácticas extramuros y se solicito se revisarán las solicitudes con los respectivos Jefes de Programa, para poder dar tramite con el presupuesto disponible
A51: 3. | B51: Mediante Circular No. 038 del 4 de octubre de 2022, se solicitó nuevamente la revisión y ajuste de las solicitudes, teniendo en cuenta el presupuesto asignado
B53: Resultado de la Circular No. 038
A54: 1. | B54: Ajuste de ruta de dos (2) prácticas de la Lic en Ciencias Naturales y Educación Ambiental, disminuyendo el costo
A55: 2. | B55: Unificación de una práctica del programa de Ing de Petróleos, reduciendo una práctica y disminuyendo el costo.
A56: 3. | B56: Eliminación de tres (3) del programa de Antropología, disminuyendo el costo.
A57: 4. | B57: Unificación de cinco (5) prácticas del programa de Biología Aplicada, disminuyendo el costo.
B59: NOVEDADES
A60: 1. | B60: El 21 de septiembre de 2022, mediante Memorando No. 005 el Consejo de Facultad de Economía y Administración, envío el aval de cuatro (4) nuevas solicitudes de prácticas extramuros para el programa de Administración Turistica y Hotelera.
A61: 2. | B61: El 28 de septiembre de 2022, mediante Memorando No. 235 el Consejo de Facultad de Economía y Administración, envío el aval de una (1) solicitud de prácticas extramuros para el programa de Administración de Empresas.

Sheet TEORICO - PRACTICOS
A1: SEDE | B1: PROGRAMA | C1: NOMBRE DE LA PRACTICA | D1: NUMERO DEL CURSO | E1: CODIGO ALFANUMERICO | F1: NOMBRE DE LA ASIGNATURA | G1: NOMBRE DEL DOCENTE | H1: TIPO VINCULACIÓN DOCENTE | I1: FECHA INICIO (dÍa/mes/año) | J1: FECHA / FIN (dÍa/mes/año) | K1: RUTA | L1: DURAC. EN DIAS | M1: No. DE ALUMNOS | N1: OBSERVACIONES | O1: CONDUCTOR | P1: COMBUSTIBLE | Q1: PEAJES | R1: PARQUEADERO | S1: IMPREVISTOS | T1: VALOR BUS EXTERNO | U1: COSTO VALOR DÍA / DOCENTE | V1: COSTO TOTAL DÍAS VIATICOS DOCENTES | W1: TOTAL
A2: NEIVA | B2: CIENCIAS NATURALES -BIOLOGIA APLICADA | C2: ORIGEN DEL UNIVERSO- CONCEPTOS Y OBSERVACIONES | D2: 173832 | E2: BEBIAPL005 | F2: BIOLOGIA CELULAR 1 | G2: MAURICIO CARILLO AVILA | H2: DE PLANTA DOCENTE | I2: 44833 | J2: 44833 | K2: NEIVA.- VILLAVIEJA-NEIVA | L2: 1 | M2: 45 | T2: 1140000 | U2: 150000 | V2: =L2*U2 -> 150000
A3: NEIVA | B3: CIENCIAS NATURALES -BIOLOGIA APLICADA | C3: VISITA AL MUSEO DE HISTORIA NATURAL DE LA UNIVERSIDAD NACIONAL DE COLOMBIA Y TALLER EN LA FUNDACION ZOOLOGICO DE SANTA CRUZ - IMPORTANCIA DE ESTUDIOS"BOTANICOS MOLECULARES Y BIOTECNOLOGICOS" Y MANEJO DE MATERIAL VEGETAL EN JARDINES BOTANICOS Y HERBARIOS | D3: 173986 173983 173979 | E3: BEBIAPL049 | F3: PRINCIPIOS DE SISTEMATICA - BIOLOGIA DEL DESARROLLO - TAXONOMIA DE EMBRIOFITOS BASALES | G3: GUISELLE NEGOVER BRIÑEZ VASQUEZ/ CARLOS ALBERTO MENDEZ | H3: CATEDRA VISITANTE DOCENTE | I3: 44834 | J3: 44835 | K3: NEIVA-BOGOTA MUSEO DE HISTORIA NATURAL UNAL-SAN ANTONIO DEL TEQUENDAMA FUNDACION ZOOLOGICO DE SANTA CRUZ-NEIVA | L3: 2 | M3: =15+11+16 -> 42 | T3: 3960000 | U3: 150000 | V3: =L3*U3 -> 300000
A4: NEIVA | B4: CIENCIAS NATURALES -BIOLOGIA APLICADA | C4: ORIGEN DEL UNIVERSO- CONCEPTOS Y OBSERVACIONES | D4: 174483 | E4: BEBIAPL005 | F4: BIOLOGIA CELULAR 2 | G4: MAURICIO CARILLO AVILA | H4: DE PLANTA DOCENTE | I4: 44833 | J4: 44833 | K4: NEIVA.- VILLAVIEJA-NEIVA | L4: 1 | M4: 8 | T4: 420000 | U4: 150000 | V4: =L4*U4 -> 150000
A5: NEIVA | B5: CIENCIAS NATURALES -BIOLOGIA APLICADA | C5: IMPORTANCIA DE COLECCIONES BOTANICAS " JARDINES BOTANICOS Y HERBARIOS" | D5: 173835 | E5: BEBIAPL013 | F5: BOTANICA | G5: CARLOS ALBERTO MENDEZ PUENTES | H5: CATEDRA VISITANTE DOCENTE | I5: 44837 | J5: 44839 | K5: NEIVA-BOGOTA-MUSEODE HISTORIA NATURAL-HERBRIO UNIVERSIDAD NACIONAL DE COLOMBIA- JARDIN BOTANICO DE BOGOTA- NEIVA | L5: 3 | M5: 29 | O5: Desiderio Olarte | P5: 400000 | Q5: 180000 | R5: 50000 | U5: 150000 | V5: =L5*U5 -> 450000
A6: NEIVA | B6: CIENCIAS NATURALES -BIOLOGIA APLICADA | C6: VISITA CENTRO DE INVESTIGACION DE BOSQUE SECO TROPICAL-ATTALEA | D6: 174341 | E6: FEBIAPL020 | F6: VALORACION DE ECOSISTEMAS | G6: GUISELLE NEGOVER BRIÑEZ VASQUEZ | H6: CATEDRA VISITANTE DOCENTE | I6: 44837 | J6: 44837 | K6: NEIVA-AREA DE COMPESACION AMBIENTAL DE LA CENTRAL HIDROELECTRICA DEL QUIMBO EN LA VEREDA PEDERNAL DEL MUNICIPIO DE AGRADO-NEIVA | L6: 1 | M6: 21 | T6: 1290000 | U6: 150000 | V6: =L6*U6 -> 150000
A7: NEIVA | B7: CIENCIAS NATURALES -BIOLOGIA APLICADA | C7: ADAPTACION DE LOS INVERTEBRADOS A LAS CONDICIONES DE CAVERNA PARQUE NACIONAL NATURAL CUEVA DE LOS GUACHAROS | D7: 173843 | E7: BEBIAPL016 | F7: BIOLOGIA DE INVERTEBRADOS | G7: JUAN CARLOS VALENZUELA | H7: CATEDRA VISITANTE DOCENTE | I7: 44839 | J7: 44842 | K7: NEIVA-PALESTINA-VEREDA MENSURA-PARQUE NACIONAL CUEVA LOS GUACHAROS- NEIVA | L7: 4 | M7: 31 | O7: Alberto Mora | P7: 150000 | Q7: 41000 | R7: 45000 | U7: 150000 | V7: =L7*U7 -> 600000
A8: NEIVA | B8: CIENCIAS NATURALES -BIOLOGIA APLICADA | C8: ESTUDIO DE BIOLOGIA DE LA CONSERVACION | D8: 174836 | E8: BEBIAPL021 | F8: BIOLOGIA DE LA CONSERVACION | G8: EDGAR ANDRES BERNAL CATRO | H8: NOMBRAMIENTO OCASIONAL DOCENTE | I8: 44848 | J8: 44851 | K8: NEIVA-RESERVA JUANCHACO, MUNICIPIO DE BUENAVENTURA CHOCO- NEIVA | L8: 4 | M8: 19 | O8: Nelson Valbuena | P8: 600000 | Q8: 350000 | R8: 75000 | U8: 150000 | V8: =L8*U8 -> 600000
A9: NEIVA | B9: CIENCIAS NATURALES -BIOLOGIA APLICADA | C9: GESTION Y CONSERVACION DE ECOSISTEMAS ESTRATEGICOS - SISTEMAS AMBIENTALES DEL HUILA | D9: 174863 174854 | E9: FEBIAPL015 | F9: ECOSISTEMAS ESTRATEGICOS - SISTEMAS AMBIENTALES | G9: DIANA POLANIA CAVIEDES | H9: CATEDRA VISITANTE DOCENTE | I9: 44855 | J9: 44858 | K9: NEIVA-TESALIA-LA ARGENTINA-PITALITO-PARQUE NACIONAL NATURAL PURACE-NEIVA | L9: 3 | M9: =12+4 -> 16 | O9: Alberto Mora | P9: 150000 | Q9: 41000 | R9: 30000 | U9: 150000 | V9: =L9*U9 -> 450000
A10: NEIVA | B10: CIENCIAS NATURALES -BIOLOGIA APLICADA | C10: RECONOCIMIENTO DE LA DIVERSIDAD BIOLOGICA | D10: 174001 | E10: BEBIAPL028 | F10: GENETICA | G10: WILSON RODRIGO CRUZ FLOR | H10: CATEDRA VISITANTE DOCENTE | I10: 44860 | J10: 44862 | K10: NEIVA-LA TRIBUNA-NEIVA | L10: 2 | M10: 24 | T10: 3380000 | U10: 150000 | V10: =L10*U10 -> 300000
A11: NEIVA | B11: CIENCIAS NATURALES -BIOLOGIA APLICADA | C11: DIVERSIDAD DE VERTEBRADOS | D11: 173939 | E11: BEBIAPL012 | F11: BIOLOGIA DE VERTEBRADOS | G11: CAROLINA LOPEZ CASTAÑEDA | H11: NOMBRAMIENTO OCASIONAL DOCENTE | I11: 44870 | J11: 44872 | K11: NEIVA-SANTA MARIA- EL PARAISO-SAN BENITO-LA VEGA GUASIMOS-NEIVA | L11: 3 | M11: 35 | T11: 4500000 | U11: 150000 | V11: =L11*U11 -> 450000
A12: NEIVA | B12: CIENCIAS NATURALES -BIOLOGIA APLICADA | C12: ECOLOGIA Y ECOSISTEMAS - HISTORIA NATURAL DE LA TRANSFORMACION ECOLOGICA | D12: 173999 173996 | E12: BEEXnull01 | F12: ECOLOGIA - HISTORIA NATURAL | G12: DIANA POLANIA CAVIEDES/ EDGAR ANDRES BERNAL CASTRO | H12: CATEDRA VISITANTE DOCENTE | I12: 44877 | J12: 44880 | K12: NEIVA - BALSILLAS - NEIVA | L12: 3 | M12: 60 | T12: 7425000 | U12: 150000 | V12: =L12*U12 -> 450000
A13: NEIVA | B13: CIENCIAS NATURALES -BIOLOGIA APLICADA | C13: SISTEMA DE PRODUCCION ACUICOLA | D13: 174867 | E13: FEBIAPL016 | F13: PRODUCCION ACUICOLA | G13: RUBEN DARIO VALBUENA VILLAREAL | H13: DE PLANTA DOCENTE | I13: 44883 | J13: 44884 | K13: NEIVA- GARZON- NEIVA | L13: 2 | M13: 12 | O13: Desierio Olarte | P13: 0 | Q13: 20000 | R13: 10000 | U13: 150000 | V13: =L13*U13 -> 300000
A14: NEIVA | B14: CIENCIAS NATURALES -BIOLOGIA APLICADA | C14: RECONOCIMIENTO GEOLOGICO GENERAL SUR DE COLOMBIA | D14: 174862 | E14: BEBIAPL054 | F14: GEOCIENCIAS | G14: INGRID NATALIA MUÑOZ | H14: DE PLANTA DOCENTE | I14: 44889 | J14: 44892 | K14: NEIVA-POPAYAN (PASTO)- NEIVA | L14: 4 | M14: 18 | O14: Alberto Mora | P14: 600000 | Q14: 150000 | R14: 60000 | S14: 0 | T14: 0 | U14: 150000 | V14: =L14*U14 -> 600000
A15: NEIVA | B15: CIENCIAS NATURALES -BIOLOGIA APLICADA | C15: RECONOCIMIENTO DE ESPERMATOFICOS EN ECOSISTEMAS SURCOLOMBIANO | D15: 173995 | E15: BEBIAPL051 | F15: TAXONOMIA DE ESPERMATOFITOS | G15: CARLOS ALBERTO MENDEZ PUENTES | H15: CATEDRA VISITANTE DOCENTE | I15: 44890 | J15: 44892 | K15: NEIVA-PALESTINA-FINCA EL ENCANTO-CUEVA DE LOS GUACHAROS-NEIVA | L15: 3 | M15: 26 | O15: Alberto Mora | P15: 150000 | Q15: 41000 | R15: 20000 | U15: 150000 | V15: =L15*U15 -> 450000
A16: NEIVA | B16: CIENCIAS NATURALES -BIOLOGIA APLICADA | C16: ECOSISTEMAS ESTRATEGICOS Y PROBLEMATICAS | D16: 174855 174865 | E16: FEBIAPL003 | F16: PAISAJE ECOLOGICO - PROBLEMATICA ECOLOGICA Y AMBIENTAL | G16: RIGOBERTO MAYOR POLANIA | H16: CATEDRA VISITANTE DOCENTE | I16: 44889 | J16: 44891 | K16: NEIVA-AIPE RESERVAS NATURALES DE BOSQUE SECO TROPICAL- FUNDACION ASOBOSPA-NEIVA | L16: 3 | M16: 9 | O16: Alberto Mora | P16: 150000 | Q16: 32000 | R16: 20000 | U16: 150000 | V16: =L16*U16 -> 450000
A17: NEIVA | B17: CIENCIAS NATURALES -BIOLOGIA APLICADA | C17: CAMPO Y ECOLOGIA | D17: 174868 | E17: FEBIAPL030 | F17: ECOLOGIA DE CAMPO | G17: CARMEN ELENA BARRAGAN RUIZ | H17: CATEDRA VISITANTE DOCENTE | I17: 44897 | J17: 44901 | K17: VEREDA MEREMBERG | L17: 3 | M17: 16 | T17: 3540000 | U17: 150000 | V17: =L17*U17 -> 450000
A18: NEIVA | B18: ANTROPOLOGIA Y ARQUEOLOGIA | C18: ZONA DE VIDA,ECOSISTEMA TERRESTRES Y ACUATICOS, RECONOCIMIENTO DE FACTORES AMBIENTALES Y BIOTICOS, E INTERACCION CON LA COMUNIDAD HUMANA | D18: 172186 | E18: BECSHAN12 | F18: ECOLOGIA Y SOCIEDAD | G18: VLADYMEER LEON CUELLAR | H18: CATEDRA DOCENTE | I18: 44885 | J18: 44885 | K18: NEIVA-CUENCA HIDROGRAFICA RIO LAS CEIBAS | L18: 1 | M18: 7 | O18: Nelson Valbuena | P18: 0 | Q18: 0 | R18: 0 | U18: 150000 | V18: =L18*U18 -> 150000
A19: NEIVA | B19: ANTROPOLOGIA Y ARQUEOLOGIA | C19: INDUSTRIA TURISTICA Y CAMBIO SOCIOCULTURAL EN EL DESIERTO DE LA TATACOA | | D19: 172169-172166 | E19: BECSHAN06 BECSHAN05 | F19: PENSAMIENTO ANTROPOLOGICO I E INTRODUCCION A LA ARQUEOLOGIA | G19: LUIS GERARDO FRANCO ARCE Y LISANDRO SOTO FLECHAS | H19: CATEDRA VISITANTE DOCENTE | I19: 44874 | J19: 44876 | K19: NEIVA-MUNICIPIO DE VILLAVIEJA- DESIERTO LA TATACOA | L19: 3 | M19: =17+19 -> 36 | T19: 680000 | U19: 30000 | V19: =L19*U19 -> 90000
A20: NEIVA | B20: ANTROPOLOGIA Y ARQUEOLOGIA | C20: VICITA A HONDA, TOLIMA Y MUSEO DEL RIO MAGDALENA | D20: 172202-172199 | E20: BECSHAN17 BECSHAN16 | F20: ARQUEOLOGIA SOCIAL Y TEORIA SOCIAL I | G20: LUIS GERARDO FRANCO ARCE Y LISANDRO SOTO FLECHAS | H20: CATEDRA VISITANTE DOCENTE | I20: 44887 | J20: 44890 | K20: NEIVA,HUILA-HONDA,TOLIMA | L20: 4 | M20: =23+27 -> 50 | O20: Nelson Valbuena | P20: 400000 | Q20: 180000 | R20: 60000 | U20: 150000 | V20: =L20*U20 -> 600000
A21: NEIVA | B21: COMUNICACION SOCIAL Y PERIODISMO | C21: ACERCAMIENTO A LAS EXPERIENCIAS TRANSMEDIA | D21: 172808 | E21: BECSHCS28 | F21: LENGUAJE Y NARRATIVA TRANSMEDIA | G21: DIEGO FERNANDO ACHURRI SIERRA | H21: CATEDRA DOCENTE | I21: 44825 | J21: 44828 | K21: NEIVA-BOGOTA-NEIVA | L21: 4 | M21: 18 | O21: Desiderio Olarte | P21: 400000 | Q21: 180000 | R21: 60000 | U21: 150000 | V21: =L21*U21 -> 600000
A22: NEIVA | B22: COMUNICACION SOCIAL Y PERIODISMO | C22: NUEVAS FORMAS DE NARRAR | D22: 172790 | E22: BECSHCS19 | F22: COMINICACION DIGITAL | G22: DIEGO FERNANDO ACHURRI SIERRA | H22: CATEDRA DOCENTE | I22: 44872 | J22: 44874 | K22: NEIVA-MEDELLIN-NEIVA | L22: 3 | M22: 29 | O22: Alberto Mora | P22: 500000 | Q22: 270000 | R22: 50000 | U22: 150000 | V22: =L22*U22 -> 450000
A23: NEIVA | B23: COMUNICACION SOCIAL Y PERIODISMO | C23: HUILA AUDIOVISUAL | D23: 172778-172784 | E23: BECSHCS09 | F23: TALLER IMAGEN FIJA G01 Y G02 | G23: FERNANDO CHARRY GONZALEZ | H23: DE PLANTA DOCENTE | I23: 44876 | J23: 44878 | K23: VILLAVIEJA Y DESIERTO LA TATACOA | L23: 3 | M23: =21+20 -> 41 | T23: 1040000 | U23: 30000 | V23: =L23*U23 -> 90000
A24: PITALITO | B24: COMUNICACION SOCIAL Y PERIODISMO | C24: PROCESOS SOCIALES Y NARRATIVAS TRANSMEDIA EN CALI | D24: 172839 | E24: BECSHCS28 | F24: LENGUAJES Y NARRATIVAS TRANSMEDIA- SEDE PITALITO | G24: OSCAR IVAN FORERO MOSQUERA | H24: NOMBRAMIENTO OCASIONAL DOCENTE | I24: 44872 | J24: 44875 | K24: NEIVA-PITALITO-CALI( RECORRIDO INTERNO)-PITALITO-NEIVA | L24: 4 | M24: 17 | O24: Desiderio Olarte - Nelson Perdomo | P24: 500000 | Q24: 500000 | R24: 75000 | U24: 150000 | V24: =L24*U24 -> 600000
A25: PITALITO- NEIVA | B25: COMUNICACION SOCIAL Y PERIODISMO | C25: ARTICULACION DE CONTEXTOS LOCALES A PRODUCCION DE NARRATIVAS SONORAS Y AUDIOVISUALES EN PASTO | D25: 172803-172837 | E25: BECSHCS18 BECSHCS20 | F25: NARRATIVAS SONORAS Y AUDIOVISUALES (SEDE NEIVA)Y METODOLOGIAS PARA LA INTERACCION - SEDE PITALITO | G25: OSCAR IVAN FORERO MOSQUERA - CLAUDIA JIMENA ZUÑIGA RAMIREZ | H25: NOMBRAMIENTO OCASIONAL DOCENTE | I25: 44822 | J25: 44825 | K25: NEIVA-PITALITO-PASTO(RECORRIDO INTERNO Y VISITA AL LAGO DEL GUAMES)- PITALITO-NEIVA | L25: 4 | M25: =18+11 -> 29 | O25: Nelson Valbuena - Jairo Gonzalez | P25: 500000 | Q25: 150000 | R25: 60000 | U25: 150000 | V25: =L25*U25 -> 600000
A26: GARZON | B26: INGENIERÍA AGRÍCOLA | C26: APLICACION DE INDICADORES PARA EL ANALISIS DE LA CALIDAD DEL AGAUA EN LA QUBRADA RIO LORO-GARZON | D26: 174798 | E26: BEEXTA12 | F26: CALIDAD DE AGUAS | G26: KAREN DANIELA QUINTERO | H26: CATEDRA VISITANTE DOCENTE | I26: 44847 | J26: 44848 | K26: QUEBRADA RIO LORO DESDE ZULUAGA HASTA EL POBLADO DE RIO LORO | L26: 2 | M26: 15 | N26: NO TIENE FORMATO MI-FOR-FO-16 | T26: 1020000
A27: GARZON | B27: INGENIERÍA AGRÍCOLA | C27: CARACTERISTICAS MORFOMETRICAS Y GEOMORFOLOGICAS DE UNA CUENCA HIDROGRAFICA | D27: 174641 | E27: BEINAG83 | F27: MANEJO DE CUENCAS HIDROGRAFICAS | G27: ALEXANDRA LUNA CUELLAR | H27: CATEDRA DOCENTE | I27: 44867 | J27: 44869 | K27: SALIDA DE GARZON-MANIZALEZ-PARQUE LOS NEVADOS-GARZON | L27: 3 | M27: 8 | N27: NO TIENE FORMATO MI-FOR-FO-16 | T27: 8400000 | U27: 150000 | V27: =L27*U27 -> 450000
A28: GARZON | B28: INGENIERÍA AGRÍCOLA | C28: PROCESO DE PRODUCCION, COSECHA, POST-COSECHA, INDUSTRIALIZACION Y COMERCIALIZACION DEL CAFE | D28: 174645 | E28: FEINAG79 | F28: TECNOLOGIA DEL CAFE | G28: LUIS FERNANDO CALDERON ALVARADO | H28: CATEDRA VISITANTE DOCENTE | I28: 44869 | J28: 44870 | K28: GARZON-EL PITAL- LA PLATA-GIGANTE-GARZON | L28: 2 | M28: 17 | N28: NO TIENE FORMATO MI-FOR-FO-16 | T28: 3120000 | U28: 150000 | V28: =L28*U28 -> 300000
A29: GARZON | B29: INGENIERÍA AGRÍCOLA | C29: DETERMINACION DE LAS PRINCIPALES PROPIEDADES MECANICAS DE LOS MATERIALES. ENSAYO DE TRACCION | D29: 174600 | E29: BEINAG12 | F29: ELEMENTOS DE MAQUINAS | G29: JUAN CARLOS MARTINEZ WALLES | H29: CATEDRA VISITANTE DOCENTE | I29: 44872 | J29: 44872 | K29: SEDE PRINCIPAL UNIVERSIDAD SURCOLOBIANA , LABORATORIO DE MATERIALES, GARZON-NEIVA-GARZON | L29: 2 | M29: 23 | O29: Nelson Valbuena | P29: 150000 | Q29: 40000 | R29: 0 | U29: 150000 | V29: =L29*U29 -> 300000
A30: GARZON | B30: INGENIERÍA AGRÍCOLA | C30: ANATOMIA EXTERNA DEL ALTO, MORFOLOGIA DE LA RAIZ, PROPIEDADES FISCIO QUIMICAS DEL AGUA, POTENCIAL HIDRICO IMBIHICION PERMEABILIDAD DE | D30: 174627 | E30: BEINAG02 | F30: FISIOLOGIA VEGETAL | G30: ERNETH PARRA MENDEZ | H30: CATEDRA VISITANTE DOCENTE | I30: 44873 | J30: 44873 | K30: GARZON-LABORATORIO FISIOLOGIA VEGETAL DE LA UNIVERSIDAD SURCOLOMBIANA, SEDE PITALITO-GARZON | L30: 1 | M30: 9 | O30: Nelson Valbuena | P30: 150000 | Q30: 41000 | R30: 0 | U30: 150000 | V30: =L30*U30 -> 150000
A31: GARZON | B31: INGENIERÍA AGRÍCOLA | C31: DESARROLLO SOSTENIBLE EN TORNO A LA FINCA AGROECOÑOGICA | D31: 174601 | E31: FEINAG64 | F31: DESARROLLO SOSTENIBLE Y MEDIO AMBIENTE | G31: MARTHA LUCIA PEÑA QUIMBAYA | H31: CATEDRA DOCENTE | I31: 44874 | J31: 44877 | K31: LA PLATA-GARZON-BOGOTA-RESTREPO VIA AL LLANO-GARZON- LA PLATA | L31: 2 | M31: 7 | N31: NO TIENE FORMATO MI-FOR-FO-16 | T31: 6620000 | U31: 150000 | V31: =L31*U31 -> 300000
A32: GARZON | B32: INGENIERÍA AGRÍCOLA | C32: POTENCIA EN QUIPOS AGRICOLAS, EQUPOS DE LABRANZA, CAPACIDAD DE TRABAJO Y PERFILES DEL CIRTE DE LOS IMPLEMENTOS AGRICOLAS | D32: 174447 | E32: BEINAG19 | F32: MAQUINAS AGRICOLAS | G32: JUAN CARLOS MARTINEZ WALLES | H32: CATEDRA VISITANTE DOCENTE | I32: 44876 | J32: 44876 | K32: GARZON-AIPE-GARZON | L32: 1 | M32: 10 | T32: 1200000 | U32: 150000 | V32: =L32*U32 -> 150000
A33: GARZON | B33: INGENIERÍA AGRÍCOLA | C33: PRACTICA INTEGRAL DE LABORATORIO FISICA MECANICA | D33: 174619 | E33: BFEXCN06 | F33: FISICA MECANICA | G33: WILLIAM ARLED SANCHEZ VARGAS | H33: CATEDRA VISITANTE DOCENTE | I33: 44876 | J33: 44876 | K33: GARZON VIA NACIONAL A PITALITO SEDE USCO-PITALITO-GARZON | L33: 1 | M33: 9 | T33: 1560000 | U33: 150000 | V33: =L33*U33 -> 150000
A34: GARZON | B34: INGENIERÍA AGRÍCOLA | C34: ESTRUCTURAS DE CLIMA CONTROLADO | D34: 174602 | E34: FEINGAGR84 | F34: DISEÑO Y CONSTRUCCION DE INVERNADEROS | G34: LUIS FERNANDO CALDERON ALVARADO | H34: CATEDRA VISITANTE DOCENTE | I34: 44876 | J34: 44877 | K34: GARZON-GIGANTE-ESPINAL-EL JUNCAL-GARZON | L34: 2 | M34: 12 | N34: NO TIENE FORMATO MI-FOR-FO-16 | T34: 1190000 | U34: 150000 | V34: =L34*U34 -> 300000
A35: GARZON | B35: INGENIERÍA AGRÍCOLA | C35: LABORATORIO MECANICA DE SUELOS | D35: 174323 | E35: BFINAG05 | F35: MECANICA DE SUELOS | G35: ERNETH PARRA MENDEZ | H35: CATEDRA VISITANTE DOCENTE | I35: 44876 | J35: 44876 | K35: UNIVERSIDAD SURCOLOMBIANA GARZON-UNIVERSIDAD SURCOLOMBIANA NEIVA | L35: 1 | M35: 11 | N35: NO TIENE FORMATO MI-FOR-FO-16 | T35: 1260000 | U35: 150000 | V35: =L35*U35 -> 150000
A36: GARZON | B36: INGENIERÍA AGRÍCOLA | C36: PRACTICA INTEGRAL DE MATERIALES DE CONTRUCCION, ELABORACION PROBETAS DE CONCRETO, DIERÑO DE MEZCLAS, GRANULOMETRIA, DENSIDAD APARENTE Y REAL PARA GRANOS GRUESOS Y FINOS, ENTRE OTRAS PRUEBAS BASICAS | D36: 174456 | E36: BEINAG20 | F36: MATERIALES DE CONSTRUCCION | G36: JOSE AGENER ZAPATA | H36: CATEDRA VISITANTE DOCENTE | I36: 44878 | J36: 44878 | K36: GARZON-NEIVA USCO SEDE CENTRAL-LABORATORIO DE MATERIALES-GARZON | L36: 1 | M36: 17 | O36: Nelson Valbuena | P36: 150000 | Q36: 40000 | R36: 0 | U36: 150000 | V36: =L36*U36 -> 150000
A37: GARZON | B37: INGENIERÍA AGRÍCOLA | C37: PRACTICA INTEGRAL | D37: 174459 | E37: BEINAG21 | F37: PRACTICA INTEGRAL | G37: JOSE AGENER ZAPATA | H37: CATEDRA VISITANTE DOCENTE | I37: 44880 | J37: 44883 | K37: GARZON- GINEBRA-PALMIRA-LA UNION-TULUA-VALENCIA-BUGA-GARZON | L37: 4 | M37: 17 | N37: NO TIENE FORMATO MI-FOR-FO-16 | T37: 12720000 | U37: 150000 | V37: =L37*U37 -> 600000
A38: GARZON | B38: INGENIERÍA AGRÍCOLA | C38: EVALUACION DE PARAMETROS Y METODOS DE RIEGO Y CARACTERIZACION DE UN DISTRITO DE RIEGO DE GRAN ESCALA | D38: 174438 | E38: BEINAG17 | F38: INGENIERIA DE RIEGOS I | G38: CARLOS CÁCERES GONZALEZ | H38: CATEDRA VISITANTE DOCENTE | I38: 44881 | J38: 44881 | K38: SALIDA DEL MUNICIPIO DE GARZON HACIA EL MUNICIPIO DEL ESPINAL, TOLIMA, DISTRITO DE RIEGO USOCOELLO-REGRESO AL MUNICIPIO DE GARZON | L38: 1 | M38: 22 | N38: NO TIENE FORMATO MI-FOR-FO-16 | T38: 1890000 | U38: 150000 | V38: =L38*U38 -> 150000
A39: GARZON | B39: INGENIERÍA AGRÍCOLA | C39: IDENTIFICACION DE LOS FACTORES Y PROCESOS QUE INCIDEN EN EL MANEJO Y CONSERVACION DE PRODUCTOS AGROPECUARIOS | D39: 174430 | E39: BEINAG15 | F39: MANEJO Y CONSERVACION DE PRODUCTOS AGROPECUARIOS | G39: OSCAR MAURICIO BERMEO | H39: NOMBRAMIENTO OCASIONAL DOCENTE | I39: 44881 | J39: 44883 | K39: GARZON-NEIVA (CESUCAFE-AGROINDUTRIA)- RIVERA (EMPRESA CACAO RIVERENSE)-PITALITO (TECNOPARQUE YAMBORÓ-CERVECERIA ARTESANAL)-TARQUI (QUESOS REYMA)-GARZON | L39: 3 | M39: 18 | N39: NO TIENE FORMATO MI-FOR-FO-16 | T39: 2400000 | U39: 150000 | V39: =L39*U39 -> 450000
A40: GARZON | B40: INGENIERÍA AGRÍCOLA | C40: DISTRITOS DE RIEGO EN EL TOLIMA, GRANJAS INTEGRALES EN FUSA, MUSEO IGAC, MUSEO GEOLOGICO COLOMBIANO, LABORATORIOS DE SUELOS UNIVERSIDAD NACIONAL AREA DE VIVEROS E | D40: 174399 | E40: BEINAG24 | F40: SUELOS | G40: ERNETH PARRA MENDEZ | H40: CATEDRA VISITANTE DOCENTE | I40: 44881 | J40: 44883 | K40: GARZON-FOSFATOS DEL HUILA, DISTRITOS DE RIEGO EN EL TOLIMA,GRANJAS INTEGRALES EN FUSA, MUSEO IGAC, MUSEO GEOLOGICO COLOMBIANO, LABORATORIO DE SUELOS UNIVERSIDAD NACIONAL REA DE VIVIEROS E | L40: 3 | M40: 16 | T40: 10350000 | U40: 150000 | V40: =L40*U40 -> 450000
A41: GARZON | B41: INGENIERÍA AGRÍCOLA | C41: PRINCIPALES FUENTES DE POTENCIA EN EL SECTOR AGRICOLA | D41: 174373 | E41: BEINAG13 | F41: FUENTES DE POTENCIA | G41: JUAN CARLOS MARTINEZ WALLES | H41: CATEDRA VISITANTE DOCENTE | I41: 44883 | J41: 44883 | K41: GARZON-CENTRO DE FORMACION AGROINDUSTRIAL LA ANGOSTURA SENA (CAMPOALEGRE), GARZON | L41: 1 | M41: 21 | N41: NO TIENE FORMATO MI-FOR-FO-16 | T41: 830000 | U41: 150000 | V41: =L41*U41 -> 150000
A42: GARZON | B42: INGENIERÍA AGRÍCOLA | C42: PRACTICA INTEGRAL DE LABORATORIO FISICA ELECTROMAGNETICA | D42: 174611 | E42: BFEXCN05 | F42: FISICA ELECTROMAGNETICA | G42: WILLIAM ARLED SANCHEZ VARGAS | H42: CATEDRA VISITANTE DOCENTE | I42: 44883 | J42: 44883 | K42: GARZON VIA NACIONAL A PITALITO SEDE USCO-PITALITO-GARZON | L42: 1 | M42: 10 | N42: NO TIENE FORMATO MI-FOR-FO-16 | T42: 1560000 | U42: 150000 | V42: =L42*U42 -> 150000
A43: GARZON | B43: INGENIERÍA AGRÍCOLA | C43: COMO CALCULAR DENSIDADES, SEPARAR MEZCLAS, ENLACES QUIMICOS, GASES Y ESTEQUIOMETRIA | D43: 174620 | E43: BFINPE06 | F43: QUIMICA GENERAL | G43: ALEXANDRA LUNA CUELLAR | H43: CATEDRA DOCENTE | I43: 44883 | J43: 44883 | K43: GARZON-VIA PRINCIPAL HASTA LA SEDE USCO PITALITO-GARZON | M43: 9 | T43: 1070000 | U43: 150000 | V43: =L43*U43 -> 0
A44: GARZON | B44: INGENIERÍA AGRÍCOLA | C44: ECOSISTEMAS TERRESTRES Y ALTERACIONES | D44: 174626 | E44: BFINAG02 | F44: ECOLOGIA | G44: ALEXANDRA LUNA CUELLAR | H44: CATEDRA DOCENTE | I44: 44884 | J44: 44885 | K44: SALIDA DE GARZON VIA INTERVEREDAL VIA AL PARAMO DE MIRAFLORES, DEL MUNICIPIO DE GARZON HUILA | L44: 2 | M44: 3 | N44: NO TIENE FORMATO MI-FOR-FO-16 | O44: Nelson Valbuena | P44: 150000 | Q44: 20000 | R44: 10000 | U44: 150000 | V44: =L44*U44 -> 300000
A45: GARZON | B45: INGENIERÍA AGRÍCOLA | C45: CARACTERIZACION DE CUENCAS Y MEDICION DE CAUDALES EN SITIO | D45: 174415 | E45: BEINAG085 | F45: HIDROCLIMATOLOGIA | G45: CARLOS CÁCERES GONZALEZ | H45: CATEDRA VISITANTE DOCENTE | I45: 44887 | J45: 44887 | K45: MUNICIPIO DE GARZON HACIA EL MUNICIPIO DE NEIVA, INSTALACIONES DEL INSTITUTO DE HIDROLOGIA, METEOROLOGIA Y ESTUDIOS AMBIENTALES Y LUEGO VIA VEREDA VEGALARGA KM 15, HASTA LLEGAR A LA BOCATOMA DEL ACUEDUCTO DEL MUNICIPIO DE NEIVA. REGRESO AL MUNICIPIO DE GARZON | L45: 1 | M45: 9 | N45: NO TIENE FORMATO MI-FOR-FO-16 | T45: 2140000 | U45: 150000 | V45: =L45*U45 -> 150000
A46: GARZON | B46: INGENIERÍA AGRÍCOLA | C46: PRACTICA INTEGRAL DE INGENIERIA DE RIEGOS 2 Y DRENAJES AGRICOLAS AL DEPARTAMENTO DEL VALLE DEL CAUCA | D46: 174444 174357 | E46: BEINAG18 BEINAG10 | F46: INGENIERIÍA DE RIEGOS II Y DRENAJES AGRICOLAS | G46: CARLOS CÁCERES GONZALEZ | H46: CATEDRA VISITANTE DOCENTE | I46: 44888 | J46: 44891 | K46: SALIDA DEL MUNICIPIO DE GARZON VIA A NEIVA HACIA LA UNION (VALLE DEL CAUCA), DISTRITO DE RIEGO ASORUT, MUNICIPIO DE PALMIRA (VALLE DEL CAUCA), LA CANDELARIA (VALLE DEL CAUCA), INGENIO DEL CAUCA-REGRESO AL MUNICIPIO DE GARZON | L46: 4 | M46: =16+24 -> 40 | N46: NO TIENE FORMATO MI-FOR-FO-16 | O46: Desiderio Olarte | P46: 450000 | Q46: 390000 | R46: 60000 | U46: 150000 | V46: =L46*U46 -> 600000
A47: GARZON | B47: INGENIERÍA AGRÍCOLA | C47: CANALES ABIERTOS Y ESTRUCTURAS HIDRAULICAS | D47: 174628 | E47: BFINAG04 | F47: HIDRAULICA | G47: LUIS FERNANDO CALDERON ALVARADO | H47: CATEDRA VISITANTE DOCENTE | I47: 44889 | J47: 44889 | K47: GARZON-PAICOL-TESALIA-GARZON | L47: 1 | M47: 14 | N47: NO TIENE FORMATO MI-FOR-FO-16 | T47: 1120000 | U47: 150000 | V47: =L47*U47 -> 150000
A48: GARZON | B48: INGENIERÍA AGRÍCOLA | C48: PROYECTO RIO LAS CEIBAS | D48: 174643 | E48: FEINAG94 | F48: MANEJO Y CONSERVACION DE SUELOS | G48: ERNETH PARRA MENDEZ | H48: CATEDRA VISITANTE DOCENTE | I48: 44890 | J48: 44890 | K48: GARZON-NEIVA-PROYECTO RIO LAS CEIBAS EN DONDE VISITAREMOS CENTRO DE INVESTIGACION, BOCATOMA EL GUAYABO, PREDIO LAS NIEVES, PREDIO LOS CAUCHOS Y PREDIO SANTA HELENA, ASI MISMO VISITAREMOS OTROS PROYECTOS QUE MANEJA LA CAM EN EL MANEJO Y CONSERVACION DE LOS | L48: 1 | M48: 20 | N48: NO TIENE FORMATO MI-FOR-FO-16 | T48: 1120000 | U48: 150000 | V48: =L48*U48 -> 150000
A49: GARZON | B49: INGENIERÍA AGRÍCOLA | C49: PRACTICA INTEGRAL DE MATERIALES DE CONTRUCCION, ELABORACION PROBETAS DE CONCRETO, DIERÑO DE MEZCLAS, GRANULOMETRIA, DENSIDAD APARENTE Y REAL PARA GRANOS GRUESOS Y FINOS, ENTRE OTRAS PRUEBAS BASICAS | D49: 174456 | E49: BEINAG20 | F49: MATERIALES DE CONSTRUCCION | G49: JOSE AGENER ZAPATA | H49: CATEDRA VISITANTE DOCENTE | I49: 44892 | J49: 44892 | K49: GARZON-NEIVA USCO SEDE CENTRAL-LABORATORIO DE MATERIALES-GARZON | L49: 1 | M49: 17 | N49: NO TIENE FORMATO MI-FOR-FO-16 | T49: 1120000 | U49: 150000 | V49: =L49*U49 -> 150000
A50: GARZON | B50: INGENIERÍA AGRÍCOLA | C50: PRACTICA ETAPAS Y FACTORES QUE BENEFICIAN Y AFECTAN LA GERMINACION | D50: 174616 | E50: BFINAG001 | F50: BIOLOGIA GENERAL | G50: ALEXANDRA LUNA CUELLAR | H50: CATEDRA DOCENTE | I50: 44894 | J50: 44894 | K50: GARZON VIA AGRADO VEREDA EL ZONA DE COMPENSACION BIOTICA DE LA HIDROELECTRICA EL QUIMBO, DEL MUNICIPIO DE EL AGRADO HUILA | L50: 1 | M50: 11 | N50: NO TIENE FORMATO MI-FOR-FO-16 | T50: 1210000 | U50: 150000 | V50: =L50*U50 -> 150000
A51: GARZON | B51: INGENIERÍA AGRÍCOLA | C51: MECANICA DE FLUIDOS | D51: 174285 | E51: BFINPE04 | F51: MECANICA DE FLUIDOS | G51: LUIS FERNANDO CALDERON ALVARADO | H51: CATEDRA VISITANTE DOCENTE | I51: 44897 | J51: 44897 | K51: GARZON-SEDE CENTRAL USCO NEIVA-LABORATORIO-GARZON | L51: 1 | M51: 21 | N51: NO TIENE FORMATO MI-FOR-FO-16 | T51: 1190000 | U51: 150000 | V51: =L51*U51 -> 150000
A52: GARZON | B52: INGENIERÍA AGRÍCOLA | C52: IDENTIFICACION DE FUENTES DE ENERGIA Y TIPOS DE MECANISMOS PARA ELPROCESO DE SECADO DE PRODUCTOS AGROPECUARIOS DE LA REGION (CACO,CAFÉ) Y OTROS | D52: 174436 | E52: BEINAG16 | F52: SECADO DE PRODUCTOS BIOLOGICOS | G52: OSCAR MAURICIO BERMEO | H52: NOMBRAMIENTO OCASIONAL DOCENTE | I52: 44918 | J52: 44920 | K52: GARZON-NEIVA (CONTEGRAL)-RIVERA (EMPRESA CACAO RIVERENSE)-SENA YAMBORÓ PITALITO- GARZON (PARQUE INDUSTRIAL PLANTA SECADO COOCENTRAL-KM 2 VIA EL AGRADO)-GARZON | L52: 3 | M52: 26 | N52: NO TIENE FORMATO MI-FOR-FO-16 | O52: Nelson Valbuena | P52: 150000 | Q52: 81000 | R52: 20000 | U52: 150000 | V52: =L52*U52 -> 450000
A53: GARZON | B53: INGENIERÍA AGRÍCOLA | C53: CONSTRUCCIONES RURALES | D53: 174349 | E53: BEINAG008 | F53: CONSTRUCCION ES RURALES | G53: JOSE AGENER ZAPATA | H53: CATEDRA VISITANTE DOCENTE | I53: 1/NOVIEMBRE/2022 CONJUNTA CON WILSON ERAZO-NEIVA | J53: 4/NOVIEMBRE/2022 CONJUNTA CON WILSON ERAZO-NEIVA | K53: SE SALE DEL MUNICIPIO DE GARZON HACIA BOGOTA, LUEGO AL MUNICIPIO DE UBAQUE-CHOACHI-FOMEQUE-INTER VEREDAL FOMEQUE Y POSTERIORMENTE AL MUNICIPIO DE | L53: 4 | M53: 19 | N53: NO TIENE FORMATO MI-FOR-FO-16 | O53: Desiderio Olarte - Nelson Perdomo | P53: 450000 | Q53: 250000 | R53: 60000 | U53: 150000 | V53: =L53*U53 -> 600000
A54: LA PLATA | B54: INGENIERÍA AGRÍCOLA | C54: EL DESARROLLO SOSTENIBLE ENTORNO A LA FINCA AGROECOLÓGICA | D54: 174420 | E54: FEINAG64 | F54: DESARROLLO SOSTENIBLE Y MEDIO AMBIENTE | G54: MARTHA LUCIA PEÑA QUIMBAYA | H54: CATEDRA DOCENTE | I54: 44852 | J54: 44855 | K54: PLATA AL MUNICIPIO DE GARZÓN PARA LUEGO DIRIGIRSE POR LA VÍA NACIONAL HACIA NEIVA Y DE ALLÍ POR LA VÍA NACIONAL HACIA BOGOTÁ Y LUEGO APROXIMADAMENTE A DOS HORAS HACIA EL DEPARTAMENTO DE META EN EL MUNICIPIO DE RESTREPO | L54: 4 | M54: 6 | O54: Nelson Valbuena | P54: 700000 | Q54: 350000 | R54: 75000 | U54: 150000 | V54: =L54*U54 -> 600000
A55: LA PLATA | B55: INGENIERÍA AGRÍCOLA | C55: QUEBRADA RÍO LORO DESDE ZULUAGA HASTA EL POBLADO DE RÍO LORO, MUNICIPIO GARZÓN. | D55: 174370 | E55: BEEXTA12 | F55: CALIDAD DE AGUAS | G55: YANET CARIDAD APIN CAMPOS | H55: CATEDRA VISITANTE DOCENTE | I55: 44852 | J55: 44852 | K55: LA PLATA- QUEBRADA RÍO LORO DESDE ZULUAGA HASTA EL POBLADO DE RÍO LORO, MUNICIPIO GARZÓN. | L55: 1 | M55: 17 | T55: 650000 | U55: 150000 | V55: =L55*U55 -> 150000
A56: LA PLATA | B56: INGENIERÍA AGRÍCOLA | C56: FLUJO DE FLUIDOS EN CONDUCTOS CERRADA MAQUINAS HIDRAULICAS LABORATORIO SEDE NEIVA (PRACTICA DE LABORATORIO). | D56: 172181 | E56: BFINPE04 | F56: MECANICA DE FLUIDOS | G56: JAVIER EDUARDO BONILLA PERDOMO | H56: NOMBRAMIENTO OCASIONAL DOCENTE | I56: 44859 | J56: 44859 | K56: LA PLATA – NEIVA (LABORATORIO SEDE ) - NEIVA (LABORATORIO SEDE ) – LA PLATA | L56: 1 | M56: 27 | T56: 1700000 | U56: 150000 | V56: =L56*U56 -> 150000
A57: LA PLATA | B57: INGENIERÍA AGRÍCOLA | C57: DIFERENTES TIPOS DE CONSTRUCCIONES AGROPECUARIAS | D57: 172504 | E57: BEINAG008 | F57: CONSTRUCCIONES RURALES | G57: EDDINSON ORTEGA MARTINEZ | H57: CATEDRA VISITANTE DOCENTE | I57: 44863 | J57: 44863 | K57: LA PLATA- GARZÓN PARA LLEGAR PRIMERO A LA PLANTA DE CAFÉ COOCENTRAL Y LUEGO GARZÓN PLANTA DE EVISCERADO QUIMBO FISH KILÓMETRO 12 VÍA A NEIVA | L57: 1 | M57: 7 | T57: 1580000 | U57: 150000 | V57: =L57*U57 -> 150000
A58: LA PLATA | B58: INGENIERÍA AGRÍCOLA | C58: LABORATORIO DE MECÁNICA DE SUELOS | D58: 172201 | E58: BFINAG05 | F58: MECANICA DE SUELOS | G58: EDDINSON ORTEGA MARTINEZ | H58: CATEDRA VISITANTE DOCENTE | I58: 44867 | J58: 44867 | K58: LA PLATA – NEIVA (SEDE CENTRAL) - LA PLATA | L58: 1 | M58: 18 | T58: 1560000 | U58: 150000 | V58: =L58*U58 -> 150000
A59: LA PLATA | B59: INGENIERÍA AGRÍCOLA | C59: CONOCIMIENTO DE PROCESOS Y OPERACIONES UNITARIAS DE LA INDUSTRIA AGROALIMENTARIA. PRINCIPALES PARÁMETROS FISICOQUÍMICOS EN LOS ALIMENTOS | D59: 172220 | E59: BEINAG15 | F59: MANEJO Y CONSERVACION DE PRODUCTOS AGROPECUARIOS | G59: YANETH LILIANA RUIZ OSORIO | H59: NOMBRAMIENTO OCASIONAL DOCENTE | I59: 44868 | J59: 44869 | K59: LA PLATA-NEIVA -LA PLATA | L59: 2 | M59: 13 | T59: 1410000 | U59: 150000 | V59: =L59*U59 -> 300000
A60: LA PLATA | B60: INGENIERÍA AGRÍCOLA | C60: PRACTICA DE LABORATORIO DE MATERIALES DE CONSTRUCCIÓN (NEIVA) | D60: 172504 | E60: BEINAG008 | F60: CONSTRUCCIONES RURALES | G60: EDDINSON ORTEGA MARTINEZ | H60: CATEDRA VISITANTE DOCENTE | I60: 44870 | J60: 44870 | K60: LA PLATA – NEIVA (SEDE CENTRAL) - LA PLATA | L60: 1 | M60: 7 | O60: Nelson Valbuena | P60: 150000 | Q60: 40000 | R60: 0 | U60: 150000 | V60: =L60*U60 -> 150000
A61: LA PLATA | B61: INGENIERÍA AGRÍCOLA | C61: VISITA ASOCIACIÓN CAFICULTORES | D61: 174454 | E61: FEINAG79 | F61: TECNOLOGIA DEL CAFE | G61: YANETH LILIANA RUIZ OSORIO | H61: NOMBRAMIENTO OCASIONAL DOCENTE | I61: 44872 | J61: 44872 | K61: LA PLATA- VEREDA ALTO CAÑADA-LA PLATA | L61: 1 | M61: 8 | O61: Desiderio Olarte | P61: 150000 | Q61: 20000 | R61: 0 | U61: 150000 | V61: =L61*U61 -> 150000
A62: LA PLATA | B62: INGENIERÍA AGRÍCOLA | C62: LABORATORIO DE PROPIEDADES FÍSICAS Y QUÍMICAS DEL SUELO | D62: 172224 | E62: BEINAG24 | F62: SUELOS | G62: CARLOS EMILIO REINA GALEANO | H62: CATEDRA DOCENTE | I62: 44872 | J62: 44872 | K62: LA PLATA – NEIVA (LABORATORIO DE SUELOS, SEDE CENTRAL USCO) | L62: 1 | M62: 20 | O62: Alberto Mora | P62: 150000 | Q62: 40000 | R62: 0 | U62: 150000 | V62: =L62*U62 -> 150000
A63: LA PLATA | B63: INGENIERÍA AGRÍCOLA | C63: RECONOCIMIENTO DE LA RESERVA MEREMBERG COMO ECOSISTEMA ESTRATÉGICO DEL DEPARTAMENTO DEL HUILA | D63: 172532 | E63: BFINAG02 | F63: ECOLOGIA | G63: ANDREA DEL PILAR CONDE CAPERA | H63: CATEDRA VISITANTE DOCENTE | I63: 44875 | J63: 44845 | K63: LA PLATA-RESERVA NATURAL MEREMBERG-LA PLATA | L63: 2 | M63: 9 | T63: 3920000 | U63: 150000 | V63: =L63*U63 -> 300000
A64: LA PLATA | B64: INGENIERÍA AGRÍCOLA | C64: LABORATORIO DE MATERIALES DE CONSTRUCCION | D64: 173301 | E64: BEINAG20 | F64: MATERIALES DE CONSTRUCCIÓN | G64: EDDINSON ORTEGA MARTINEZ | H64: CATEDRA VISITANTE DOCENTE | I64: 44877 | J64: 44877 | K64: LA PLATA – NEIVA (SEDE CENTRAL) - LA PLATA | L64: 1 | M64: 15 | T64: 1560000 | U64: 150000 | V64: =L64*U64 -> 150000
A65: LA PLATA | B65: INGENIERÍA AGRÍCOLA | C65: "PRACTICA INTEGRAL PARA EL RECONOCIMIENTO DE COMPONENTES Y SISTEMAS DE RIEGO POR ASPERSIÓN, LOCALIZADOS Y POR GRAVEDAD." | D65: 172501 | E65: BEINAG18 | F65: INGENIERÍA DE RIEGOS II | G65: JAVIER EDUARDO BONILLA PERDOMO | H65: NOMBRAMIENTO OCASIONAL DOCENTE | I65: 44880 | J65: 44883 | K65: LA PLATA - NEIVA – EL VALLE(CAUCA) - EL VALLE (CAUCA ) - NEIVA – LA PLATA | L65: 4 | M65: 10 | O65: Nelson Valbuena - Jairo Gonzalez | P65: 500000 | Q65: 350000 | R65: 60000 | U65: 150000 | V65: =L65*U65 -> 600000
A66: LA PLATA | B66: INGENIERÍA AGRÍCOLA | C66: RECONOCIMIENTO DE LA CUENCA HIDROGRÁFICA RÍO LAS CEIBAS E IDENTIFICACIÓN DE PRÁCTICAS DE MANEJO Y CONSERVACIÓN REALIZADAS EN LA CUENCA. | D66: 174429 | E66: FEINAG94 | F66: MANEJO Y CONSERVACION DE SUELOS | G66: ANDREA DEL PILAR CONDE CAPERA | H66: CATEDRA VISITANTE DOCENTE | I66: 44882 | J66: 44883 | K66: LA PLATA H - NEIVA - CUENCA RÍO LA S CEIBAS - NEIVA - LA PLATA H | L66: 1 | M66: 5 | T66: 2620000 | U66: 150000 | V66: =L66*U66 -> 150000
A67: LA PLATA | B67: INGENIERÍA AGRÍCOLA | C67: RECONOCIMIENTO DE SISTEMAS DE DRENAJES AGRICOLAS Y SU EFICIENCIA EN EL SECTOR PRODUCTIVO COLOBIANO | D67: 172505 | E67: BEINAG10 | F67: DRENAJES AGRICOLAS | G67: JOSE LEANDRO FIERRO CUELLAR | H67: CATEDRA VISITANTE DOCENTE | I67: 44887 | J67: 44890 | K67: VALLE DEL CAUCA: CENTRO DE INVESTIGACION DE AGRICULTURA TROPICAL-CIAT CENTRO DE INVESTIGACION DE LA CAÑA DE AZUCAR-CENICAÑA INGENIO AZUCARERO MANUELITA-CENTRO AGROPECUARIO DE BUGA CENTRO DE INVESTIGACION DE LA CAÑA DE AZUCAR-CENICAÑA INGENIO AZUCARERO MANUELITA-CENTRO AGROPECUARIO DE BUGA- LA PLATA | L67: 3 | M67: 3 | N67: NO TIENE FORMATO MI-FOR-FO-16 | O67: Desiderio Olarte | P67: 400000 | Q67: 390000 | R67: 40000 | U67: 150000 | V67: =L67*U67 -> 450000
A68: LA PLATA | B68: INGENIERÍA AGRÍCOLA | C68: RECONOCIMIENTO DE SISTEMAS DE DRENAJES AGRÍCOLAS Y SU EFICIENCIA EN EL SECTOR PRODUCTIVO COLOMBIANO | D68: 172505 | E68: BEINAG10 | F68: DRENAJES AGRICOLAS | G68: JOSE LEANDRO FIERRO CUELLAR | H68: CATEDRA VISITANTE DOCENTE | I68: 44887 | J68: 44890 | K68: VALLE DEL CAUCA: CENTRO DE INVESTIGACIÓN DE AGRICULTURA TROPICAL – CIAT CENTRO DE INVESTIGACIÓN DE LA CAÑA DE AZÚCAR – CENICAÑA INGENIO AZUCARERO MANUELITA CENTRO DE INVESTIGACIÓN DE LA CAÑA DE AZÚCAR – CENICAÑA INGENIO AZUCARERO MANUELITA-CENTRO AGROPECUARIO DE BUGA CENTRO DE INVESTIGACIÓN DE LA CAÑA DE AZÚCAR – CENICAÑA INGENIO AZUCARERO MANUELITA-CENTRO AGROPECUARIO DE BUGA-LA PLATA | L68: 3 | M68: 3 | O68: Nelson Valbuena - Jairo Gonzalez | P68: 400000 | Q68: 390000 | R68: 40000 | U68: 150000 | V68: =L68*U68 -> 450000
A69: LA PLATA | B69: INGENIERÍA AGRÍCOLA | C69: RECONOCIMIENTO DE LAS PRINCIPALES OBRAS QUE COMPONEN UN DISTRITO DE RIEGO | D69: 172196 | E69: BFINAG04 | F69: HIDRÁULICA | G69: RAFAEL DAVID ANGEL GASCA | H69: CATEDRA VISITANTE DOCENTE | I69: 44889 | J69: 44891 | K69: LA PLATA-DISTRITO DE RIEGO EL JUNCAL- NEIVA- VILLAVIEJA-SAN ALFONSO-DISTRITO DE RIEGO USO ALFONSO- NEIVA- LA PLATA | L69: 3 | M69: 18 | T69: 7740000 | U69: 150000 | V69: =L69*U69 -> 450000
A70: LA PLATA | B70: INGENIERÍA AGRÍCOLA | C70: LA IDENTIFICACIÓN, RECONOCIMIENTO Y MUESTREO DE SUELOS ES UNA PRÁCTICA FUNDAMENTAL QUE REQUIERE ESPECIAL CUIDADO Y CONOCIMIENTO, CON EL PROPÓSITO DE TENER LA DEBIDA MEDICIÓN Y VALORACIÓN DE LAS CARACTERÍSTICAS FÍSICAS, QUÍMICAS Y BIOLÓGICAS DEL SUELO QUE PERMITA LA TOMA DE DECISIONES DEL PRODUCTOR AGRÍCOLA. | D70: 172224 | E70: BEINAG24 | F70: SUELOS | G70: CARLOS EMILIO REINA GALEANO | H70: CATEDRA DOCENTE | I70: 44890 | J70: 44892 | K70: LA PLATA- NEIVA – BOGOTÁ - NEIVA-LA PLATA RUTA: LA PLATA- NEIVA – BOGOTÁ - NEIVA-LA PLATA | L70: 3 | M70: 20 | O70: Nelson Valbuena | P70: 400000 | Q70: 220000 | U70: 150000 | V70: =L70*U70 -> 450000
A71: LA PLATA | B71: INGENIERÍA AGRÍCOLA | C71: SISTEMAS DE PRODUCCION AGRICOLA EN AMBIENTES CONTROLADOS | D71: 174453 | E71: FEINAG97 | F71: MANEJO DE CULTIVOS EN INVERNADERO | G71: JOSE LEANDRO FIERRO CUELLAR | H71: CATEDRA VISITANTE DOCENTE | I71: 44895 | J71: 44895 | K71: LA PLATA- CENTRO DE FORMACION AGROINDUSTRIAL, SENA CAMPOALEGRE-LA PLATA | L71: 1 | M71: 35 | N71: NO TIENE FORMATO MI-FOR-FO-16 | O71: Nelson Valbuena | P71: 100000 | Q71: 20000 | R71: 0 | U71: 150000 | V71: =L71*U71 -> 150000
A72: LA PLATA | B72: INGENIERÍA AGRÍCOLA | C72: SISTEMAS DE PRODUCCIÓN AGRÍCOLA EN AMBIENTES CONTROLADOS | D72: 174453 | E72: FEINAG97 | F72: MANEJO DE CULTIVO EN INVERNADERO | G72: JOSE LEANDRO FIERRO CUELLAR | H72: CATEDRA VISITANTE DOCENTE | I72: 44895 | J72: 44895 | K72: LA PLATA-CENTRO DE FORMACION AGROINDUSTRIAL, SENA CAMPOALEGRE-LA PLATA | L72: 1 | M72: 35 | P72: 0 | Q72: 0 | R72: 0 | U72: 150000 | V72: =L72*U72 -> 150000
A73: LA PLATA | B73: INGENIERÍA AGRÍCOLA | C73: FORMAS DE UTILIZAR LAS FOTOGRAFIAS AÉREAS Y LAS IMÁGENES SATELITALES EN LOS PROCESOS DE DESARROLLO DEL SISTEMA PRODUCTIVO AGRÍCOLA;PARTIENDO DE LA GEOMÁTICA Y LOS SIG | D73: 172534 174384 | E73: BEINAG94 FEEXTA05 | F73: GEOMÁTICA Y SIG | G73: JOSE LEANDRO FIERRO CUELLAR | H73: CATEDRA VISITANTE DOCENTE | I73: 44902 | J73: 44904 | K73: CENTRO DE INVESTIGACION DE LA CAÑA-CENICAÑA; SAN ANTONIO DE LOS CABALLEROS- FLORIDA, VALLE DEL CAUCA EMPRESA AGROAP; SANTIAGO DE CALI, VALLE DEL CAUCA | L73: 3 | M73: =10+0 -> 10 | N73: NO TIENE FORMATO MI-FOR-FO-16 | O73: Desiderio Olarte - Nelson Perdomo | P73: 450000 | Q73: 350000 | R73: 40000 | U73: 150000 | V73: =L73*U73 -> 450000
A74: LA PLATA | B74: INGENIERÍA AGRÍCOLA | C74: FORMAS DE UTILIZAR LAS FOTOGRAFÍAS AÉREAS Y LAS IMÁGENES SATELITALES EN LOS PROCESOS DE DESARROLLO DEL SISTEMA PRODUCTIVO AGRÍCOLA; PARTIENDO DE LA GEOMÁTICA Y LOS SIG. | D74: 172534 174384 | E74: BEINAG94 | F74: GEOMÁTICA Y SIG | G74: JOSE LEANDRO FIERRO CUELLAR | H74: CATEDRA VISITANTE DOCENTE | I74: 44902 | J74: 44904 | K74: CENTRO DE INVESTIGACION DE LA CAÑA – CENICAÑA; SAN ANTONIO DE LOS CABALLEROS – FLORIDA, VALLE DEL CAUCA EMPRESA AGROAP; SANTIAGO DE CALI, VALLE DEL CAUCA | L74: 3 | M74: =10+0 -> 10 | O74: Nelson Valbuena - Jairo Gonzalez | P74: 450000 | Q74: 350000 | R74: 40000 | U74: 150000 | V74: =L74*U74 -> 450000
A75: LA PLATA | B75: INGENIERÍA AGRÍCOLA | C75: LABORATORIO FISICA MECÁNICA | D75: 172513 | E75: BFEXCN06 | F75: FISICA MECANICA | G75: CARLOS ALBERTO PALOMA RAMOS | H75: CATEDRA DOCENTE | I75: 15/octubre/2022 y 12/noviembre/2022 | J75: 15/octubre/2022 y 12/noviembre/2022 | K75: LA PLATA-NEIVA-LA PLATA | L75: 2 | M75: =36 -> 36 | T75: 2260000 | U75: 150000 | V75: =L75*U75 -> 300000
A76: LA PLATA | B76: INGENIERÍA AGRÍCOLA | C76: LABORATORIO FÍSICA ELECTROMAGNÉTICA | D76: 172518 | E76: BFEXCN05 | F76: FISICA ELECTROMAGNETICA | G76: ARBEY SANCHEZ RODRIGUEZ | H76: CATEDRA DOCENTE | I76: 5/noviembre/2022 y 26/noviembre/2022 | J76: 5/noviembre/2022 y 26/noviembre/2022 | K76: LA PLATA-NEIVA-LA PLATA | L76: 2 | M76: 9 | T76: 3400000 | U76: 150000 | V76: =L76*U76 -> 300000
A77: NEIVA | B77: INGENIERÍA AGRÍCOLA | C77: LABORATORIO DE HIDRÁULICA FACULTAD DE INGENIERIA DE LA UNIVERSIDAD SURCOLOMBIANA SEDE NEIVA (PRACTICA DE LABORATORIO EN LA FACULTAD DE INGENIERIA NO | D77: 175137 | E77: BEINAG18 | F77: INGENIERÍA DE RIEGOS II | G77: MARLIO BEDOYA CARDOSO | H77: DE PLANTA DOCENTE | I77: 44833 | J77: 44833 | K77: FACULTAD DE INGENIERIA (NO SE REQUIERE TRANSPORTE) | L77: 1 | M77: =14 -> 14 | P77: 0 | Q77: 0 | R77: 0
A78: NEIVA | B78: INGENIERÍA AGRÍCOLA | C78: PRACTICA INTEGRAL PARA EL RECONOCIMIENTO DE COMPONENTES Y SISTEMAS DE RIEGO POR ASPERSION, LOCALIZADOSW Y POR GRAVEDAD EN EL DISTRITO DE RIEGO EL RUT EN EL NORTE DEL VALLE DEL CAUCA. REQUIERE TRANSPORTE | D78: 175137 | E78: BEINAG18 | F78: INGENIERÍA DE RIEGOS II | G78: MARLIO BEDOYA CARDOSO | H78: DE PLANTA DOCENTE | I78: 44838 | J78: 44841 | K78: NEIVA-DISTRITO DE RIEGO RUT EN LOS MUNICIPIOS DE ROLDANILLO, LA UNION Y EL TORO EN EL NORTE DEL VALLE CAUCA- DISTRITO DE RIEGO RUT EN LOS MUNICIPIOS DE ROLDANILLO, LA UNION Y EL TORO EN EL NORTE DEL VALLE DEL CAUCA-NEIVA | L78: 4 | M78: =14 -> 14 | T78: 12800000 | U78: 271546 | V78: =L78*U78 -> 1086184
A79: NEIVA | B79: INGENIERÍA AGRÍCOLA | C79: VISITA DE CONSTRUCCIONES RURALES A LOS MUNICIPIOS DE FOMEQUE Y UBAQUE EN EL DEPARTAMENTO DE CUNDINAMARCA, PARA VISITAR EXPLOTACIONES AGROPECUARAS EN DONDE SE PUEDA OBSERVAR DISEÑOS VANGUARDISTAS, TECNOLOGIA, MECANIZACION Y AUTOMATIZACION DE SUS PROCESOS. | D79: 175141 | E79: BEINAG008 | F79: COSNTRUCCCIONES RURALES | G79: WILSON JAVIER ERAZO ESPINOZA | H79: DE PLANTA DOCENTE | I79: 44887 | J79: 44890 | K79: SE SALE DE LA CIUDAD DE NEIVA HACIA LA CIUDAD DE BOGOTÁ, LUEGO AL MUNICIPIO DE UBAQUE- CHOACHÍ FOMEQUE-INTER VEREDAL FOMEQUE Y POSTERIORMENTE A LA CIUDAD DE NEIVA | L79: 4 | M79: 22 | O79: Desiderio Olarte | P79: 400000 | Q79: 180000 | R79: 75000 | U79: 271546 | V79: =L79*U79 -> 1086184
A80: NEIVA | B80: INGENIERÍA AGRÍCOLA | C80: ESCENARIOS COMERCIALES COMO HERRAMIENTAS PARA REALIZAR UN PLAN DE NEGOCIOS | D80: 175131 | E80: BEINAG80 | F80: PLAN DE NEGOCIOS | G80: ORLANDO GUZMAN | H80: DE PLANTA DOCENTE | I80: 44861 | J80: 44863 | K80: LAS CHARLAS DENTRO DE LAS CISITAS SE REALIZARÁN DENTRO DE LA CIUDAD DE BOGOTÁ. LA VISITA A SEINPET, SE REALIZA CERCA A SUBA. | L80: 3 | M80: =15 -> 15 | T80: 7260000 | U80: 444947 | V80: =L80*U80 -> 1334841
A81: NEIVA | B81: INGENIERÍA AGRÍCOLA | C81: PRACTICA INTERAL PARA LA IDENTIFICACIÓN DE LAS PRINCIPALES OBRAS HIDRAUILICAS QUE CONFORMAN UN DITRITO DE RIEGO DE CANALES ABIERTOS E IDENTIFICACIÓN Y EVALUACION DE LAS DIFERENTES SECCIONES GEOMETRICAS DE CANALES ABIERTOS. (PRACTICA EXTRAMURO) | D81: 175000 | E81: BFINAG04 | F81: HIDRÁULICA | G81: NADIA BRIGITE SANABRIA MÉNDEZ | H81: DE PLANTA DOCENTE | I81: 44867 | J81: 44868 | K81: DISTRITO DE RIEGO EL JUNCAL (EL JUNCAL) RUTA: NEIVA-DISTRITO DE RIEGO EL JUNCAL-NEIVA OBSERVACION: ESTA RUTA SE REALIZÁ EL PRIMER DIA DE PRACTICA, SALIENDO A LA 1:00 P.M Y REGRESANDO A LAS 06:00PM DISTRITO DE RIEGO USO ALFONSO (SAN ALFONSO-VILLAVIEJA) RUTA:NEIVA-DISTRITO DE RIEGO USO ALFONSO- SAN ALFONSO VILLAVIEJA-NEIVA OBSERVACIÓN: ESTA RUTA SE REALIZARÁ EL SEGUNDO DIA DE PRACTICA, SALIENDO A LAS 7:00 A.M Y REGRESANDO A LAS 5:00 PM ES IMPORTANTE PARA ESTA RUTA CONTAR CON DOS BUSES PEQUEÑOS DEBIDO A QUE EL ACCESO A LOS DISTRITOS ES POR CARRETERAS ANGOSTAS Y SIN PAVIMENTAR, DIFICULTANDO ASI EL TRÁNSITO DE BUSES GRANDES. | L81: 2 | M81: 28 | T81: 2440000 | U81: 150000 | V81: =L81*U81 -> 300000
A82: NEIVA | B82: INGENIERÍA AGRÍCOLA | C82: PRACTICA INTERAL PARA LA IDENTIFICACIÓN DE LAS PRINCIPALES OBRAS HIDRAUILICAS QUE CONFORMAN UN DITRITO DE RIEGO DE CANALES ABIERTOS E IDENTIFICACIÓN Y EVALUACION DE LAS DIFERENTES SECCIONES GEOMETRICAS DE CANALES ABIERTOS. (PRACTICA EXTRAMURO) | D82: 174999 | E82: BFINAG04 | F82: HIDRÁULICA | G82: NN CATEDRA | H82: CATEDRA DOCENTE | I82: 44868 | J82: 44869 | K82: DISTRITO DE RIEGO EL JUNCAL (EL JUNCAL) Y DISTRITO DE RIEGO USO ALFONSO (SAN ALFONSO-VILLAVIEJA) | L82: 2 | M82: 32 | T82: 2000000 | U82: 150000 | V82: =L82*U82 -> 300000
A83: NEIVA | B83: INGENIERÍA AGRÍCOLA | C83: DIVERSIDAD Y VARIEDADES CULTIVO CAFE, COSECHA Y BENEFICIO HUMEDO , PROCESAMIENTO Y VENTA | D83: 175108 | E83: FEINAG79 | F83: ELECTIVA TECNICA TECONOLOGIA DEL CAFE | G83: BERTULFO DELGADO JOVEN | H83: CATEDRA VISITANTE DOCENTE | I83: 44889 | J83: 44890 | K83: 1. FINCA EL BARRANCO, MUNICIPIO DE SAN AGUSTIN CARRETERA NACIONAL Y CARRETERA VEREDAL 2, FINCA BELLA VISTA VEREDA FÁTIMA, BRUSELAS PITALITRO CARRETERA NACIONAL Y CARRETERA VEREDAL | L83: 2 | M83: 14 | T83: 3280000 | U83: 150000 | V83: =L83*U83 -> 300000
A84: NEIVA | B84: INGENIERÍA AGRÍCOLA | C84: SISTEMAS DE SECADO SOLAR Y MECANICO: CAFE, TABACO Y OTROS | D84: 175092 | E84: BEINAG16 | F84: SECADO DE PRODUCTOS BIOLOGICOS | G84: NESTOR ENRIQUE CERQUERA | H84: DE PLANTA DOCENTE | I84: FECHA PENDIENTE POR DEFINIR | K84: NEIVA, CAMPOALEGRE: SENA LA ANGOSTURA; GARZON; FINCAS TABACALERAS; PITALITO: CON DESPLAZAMIENTO A TECNOPARQUE YAMBORO, FINCAS CAFETERAS ZONA DE LA VEREDA BRUSELAS, FINCA 1810 VEREDA SANTA RITA; GARZON: COOCENTRAL;Y NEIVA. | M84: 20 | N84: NO TIENE FECHA, NI NUMERO DE DIAS, NI NUMERO DE ALUMNOS, NO TIENE FORMATO MI-FOR-FO-16 | U84: 150000 | V84: =L84*U84 -> 0
A85: NEIVA | B85: INGENIERÍA AGRÍCOLA | C85: VISITA A PLANTAS AGROINDUSTRIALES Y FABRICAS DE EQUIPOS DE PROCESAMIENTO DE PRODUCTOS AGROPECUARIOS | D85: 175090 | E85: BEINAG15 | F85: MANEJO Y CONSERVACIO DE PRODUCTOS AGROPECUARIOS | G85: NESTOR ENRIQUE CERQUERA | H85: DE PLANTA DOCENTE | I85: FECHA PENDIENTE POR DEFINIR | K85: NEIVA, BOGOTA, CON DESPLAZAMIENTOS DE BOGOTA AL MUNICIPIO DE MOSQUERA, MOSQUERA-BOGOTA Y EN LA ZONA URBANA DE BOGOTA, NEIVA. | M85: 17 | N85: NO TIENE FECHA, NI NUMERO DE DIAS, NI NUMERO DE ALUMNOS, NO TIENE FORMATO MI-FOR-FO-16 | U85: 150000 | V85: =L85*U85 -> 0
A86: NEIVA | B86: INGENIERÍA AGRÍCOLA | C86: ADECUACION, SALINIDAD Y DRENAJE | D86: 175140 | E86: BEINAG10 | F86: DRENAJE AGRICOLA | G86: ARMANDO TORRENTE TRUJILLO | H86: DE PLANTA DOCENTE | I86: FECHA PENDIENTE POR DEFINIR | K86: NEIVA-PALMIRA-CERRITO-CANDELARIA-NEIVA | M86: 17 | N86: NO TIENE FECHA, NI NUMERO DE DIAS, NI NUMERO DE ALUMNOS, NO TIENE FORMATO MI-FOR-FO-16 | U86: 150000 | V86: =L86*U86 -> 0
A87: NEIVA | B87: INGENIERÍA AGRÍCOLA | C87: PRACTICA INTEGRAL DE SUELOS | D87: 175223 | E87: BEINAG24 | F87: SUELOS | G87: ARMANDO TORRENTE TRUJILLO | H87: DE PLANTA DOCENTE | I87: FECHA PENDIENTE POR DEFINIR | K87: NEIVA-BOGOTÁ-NEIVA | M87: 14 | N87: NO TIENE FECHA, NI NUMERO DE DIAS, NI NUMERO DE ALUMNOS, NO TIENE FORMATO MI-FOR-FO-16 | U87: 578425 | V87: =L87*U87 -> 0
A88: NEIVA | B88: INGENIERÍA AGRÍCOLA | C88: VISITA INSTALACION DE CONCREHUILA (PLANTA DE FABRICACION CONCRETO DE CALIDA) | D88: 175122 | E88: BEINAG20 | F88: MATERIALES DE CONSTRUCCION | G88: MAURICIO DUARTE TORO | H88: DE PLANTA DOCENTE | K88: NEIVA-TESALIA-NEIVA | L88: 1 | M88: 23 | N88: NO TIENE FECHA, NI NUMERO DE DIAS, NI NUMERO DE ALUMNOS, NO TIENE FORMATO MI-FOR-FO-16 | U88: 150000 | V88: =L88*U88 -> 150000
A89: PITALITO | B89: INGENIERÍA AGRÍCOLA | C89: VISITA PLANTAS DE TRATAMIENTO DE AGUAS RESIDUALES DOMESTICAS MUNICIPALES Y PLANTA DE APROVECHAMIENTO DE RESIDUOS SOLIDOS | D89: 173419 | E89: FEINAG86 | F89: SANEAMIENTO RURAL | G89: EDINSON MUJICA RODRIGUEZ | H89: NOMBRAMIENTO OCASIONAL DOCENTE | I89: 44867 | J89: 44869 | K89: PAOCOS (PRODUCTOS LIMPIOS SAN AGUSTIN, FINCA LA FLORIDA A 5KM DEL CENTRO DE SAN AGUSTIN), PLANTYA RESIDUOS ORGANICOS BIORGANICOS VIA SAN AGUSTIN, PLANTAS DE TRATAMIENTO DE AGUAS RESIDUALES DOMESTICAS MUNICIPALES. RUTA: PITALITO, SAN AGUSTIN, PITALITO, TIMANA, HOBO, NEIVA, YAGUARA, PALERMO, BARRIO VILLA CONSTANZA (NEIVA), CAMPOALEGR, HOBO, TIMANA, PITALITO | L89: 3 | M89: 6 | N89: NO TIENE FORMATO MI-FOR-FO-16 | T89: 5370000 | U89: 150000 | V89: =L89*U89 -> 450000
A90: PITALITO | B90: INGENIERÍA AGRÍCOLA | C90: VISITA EMPRESAS VARIAS RESPECTO A LA PRODUCCION DE VALCULAS, SISTEMAS DE RIEGO, DRENAJE, BOMBEO Y OTROS, INSTALACIONES UNIVERSIDAD NACIONAL DE COLOMBIA (LABORATORIOS DE HIDRAULICA, RIEGO Y DRENAJE) | D90: 172688 | E90: BFINPE04 | F90: MECANICA DE FLUIDOS | G90: JHON JAIRO BELTRAN DIAZ | H90: NOMBRAMIENTO OCASIONAL DOCENTE | I90: 44873 | J90: 44876 | K90: PITALITO-UNIVERSIDAD NACIONAL DE COLOMBIA, ASPERSORES DE COLOMBIANA BOMBAS IHM, BERNES, OBSERVACION EJE AMBIENTAL CALLE 13 CIUDAD DE BOGOTA-PITALITO | L90: 4 | M90: 26 | N90: NO TIENE FORMATO MI-FOR-FO-16 | T90: 10160000 | U90: 150000 | V90: =L90*U90 -> 600000
A91: PITALITO | B91: INGENIERÍA AGRÍCOLA | C91: CONOCE EL HERBARIO DE LA UNIVERSIDAD SURCOLOMBIANA SEDE NEIVA PARA APROPIAR LOS CONOCIMIENTOS TEORICOS FRENTE A LA RECOPILACION E IDENTIFICACION DE LAS PLANTAS | D91: 172445 | E91: BFINAG001 | F91: BIOLOGIA GENERAL | G91: DAMARIS PERDOMO MEDINA | H91: CATEDRA VISITANTE DOCENTE | I91: 44873 | J91: 44873 | K91: UNIVERSIDAD SURCOLOMBIANA (PITALIYO)-UNIVERSIDAD SURCOLOMBIANA (NEIVA)-PITALITO | L91: 1 | M91: 18 | T91: 2940000 | U91: 150000 | V91: =L91*U91 -> 150000
A92: PITALITO | B92: INGENIERÍA AGRÍCOLA | C92: TECNIFICACION DE DRENAJE AGRICOLA SUBSUPERFICIAL-VALLE DEL CAUCA | D92: 172812 | E92: BEINAG10 | F92: DRENAJES AGRICOLAS | G92: EDINSON MUJICA RODRIGUEZ | H92: NOMBRAMIENTO OCASIONAL DOCENTE | I92: 44873 | J92: 44876 | K92: PITALITO, NEIVA,NATAGAIMA,ESPINAL,PALMIRA,INGENIOS AZUCAREROS CAUCA Y PROVIDENCIA, PALMASECA, ANDALUCIA | L92: 4 | M92: 10 | N92: NO TIENE FORMATO MI-FOR-FO-16 | O92: Nelson Valbuena - Jairo Gonzalez | P92: 550000 | Q92: 390000 | R92: 60000 | U92: 150000 | V92: =L92*U92 -> 600000
A93: PITALITO | B93: INGENIERÍA AGRÍCOLA | C93: IDENTIFICACION DE LOS FACTORES Y PROCESOS QUE INCIDEN EN EL MANEJO Y CONSERVACION DE PRODUCTOS AGROPECUARIOS | D93: 172770 | E93: BEINAG15 | F93: MANEJO Y CONSEVARCION DE PRODUCTOS AGROPECUARIOS | G93: VICTOR MANUEL MARTINEZ CASTRO | H93: NOMBRAMIENTO OCASIONAL DOCENTE | I93: 44876 | J93: 44876 | K93: SEDE USCO PITALITO-ISNOS (PANELEROS TECNIFICADOS DEL HUILA)-PITALITO-BRUSELAS (GRUPO ASOCIATIVO CAFE SALOMON, EMPRESA CANNAGUSTIN) | L93: 1 | M93: 6 | N93: NO TIENE FORMATO MI-FOR-FO-16 | T93: 620000 | U93: 150000 | V93: =L93*U93 -> 150000
A94: PITALITO | B94: INGENIERÍA AGRÍCOLA | C94: CONTEXTUALIZACION EN GESTION DE INVERNADEROS AUTOMATIZADOS Y DE OPERACION CONVENCIONAL | D94: 173417 | E94: FEINAG97 | F94: MANEJO DE CULTIVOS EN INVERNADERO | G94: YONY ARLEY CHAVEZ PARRA | H94: CATEDRA DOCENTE | I94: 44876 | J94: 44877 | K94: PITALITO-TIMANA-ALTAMIRA-GARZON- GIGANTE-HOBO-CAMPOALEGRE-NEIVA | L94: 2 | M94: 14 | N94: NO TIENE FORMATO MI-FOR-FO-16 | T94: 1810000 | U94: 150000 | V94: =L94*U94 -> 300000
A95: PITALITO | B95: INGENIERÍA AGRÍCOLA | C95: VISITA A DISTRITO Y SISTEMAS DE RIEGO A FLUJO A PRESION | D95: 172788 | E95: BEINAG17 | F95: INGENIERIA DE RIEGOS I | G95: JHON JAIRO BELTRAN DIAZ | H95: NOMBRAMIENTO OCASIONAL DOCENTE | I95: 44877 | J95: 44880 | K95: SEDE USCO PITALITO, DISTRITOS NUEVOS MUNICIPIO DE GIGANTE, GARZON Y COLOMBIA HUILA | L95: 3 | M95: 13 | N95: NO TIENE FORMATO MI-FOR-FO-16 | T95: 3900000 | U95: 150000 | V95: =L95*U95 -> 450000
A96: PITALITO | B96: INGENIERÍA AGRÍCOLA | C96: VISITA A DISTRITOS DE RIEGO OVEJERAS E IGUA EN CAMPOALEGRE, ESTRUCTURAS HIDRAULICAS REPRESA DE BETANIA, DISTRITO DE RIEGO JUNCAL MUNICIPIO DE PALERMO Y SAN ALFONSO EN VILLLAVIEJA, DESIERTO DE LA TATACOA. PITALITO | D96: 172750 | E96: BFINAG04 | F96: HIDRAULICA | G96: JHON JAIRO BELTRAN DIAZ | H96: NOMBRAMIENTO OCASIONAL DOCENTE | I96: 44885 | J96: 44888 | K96: SEDE USCO PITALITO, DISTRITO DE RIEGO OVEJERAS E IGUA, ESTRUCTURAS HIDRAULICAS REPRESA DE BETANIA. DISTRITO DE RIEGO EL JUNCAL, DISTRITO DE RIEGO USOALFONSO EN EL MUNICIPIO DE VILLAVIEJA Y DESIERTO DE LA TATCOA EN EL DEPARTAMENTO DEL HUILA | L96: 3 | M96: 18 | N96: NO TIENE FORMATO MI-FOR-FO-16 | O96: Desiderio Olarte | P96: 150000 | Q96: 82000 | R96: 20000 | U96: 150000 | V96: =L96*U96 -> 450000
A97: PITALITO | B97: INGENIERÍA AGRÍCOLA | C97: PRACTICA FUENTES DE POTENCIA (SEDE PITALITO SEME VII) | D97: 172791 | E97: BEINAG13 | F97: FUENTES DE POTENCIA | G97: AUGUSTO ISRAEL LOPEZ ARMERO | H97: NOMBRAMIENTO OCASIONAL DOCENTE | I97: 44886 | J97: 44887 | K97: PITALITO-CAMPO ALEGRE- NEIVA-PALERMO-PITALITO | L97: 2 | M97: 13 | T97: 4120000 | U97: 150000 | V97: =L97*U97 -> 300000
A98: PITALITO | B98: INGENIERÍA AGRÍCOLA | C98: RECONOCIMIENTO DE LA RESERVA DE LA SOCIEDAD CIVIL EL ENCANTO PARA INDETIFICAR LAS ESPECIES BIOTICAS Y ABIOTICAS EXISTENTES EN NUESTRA REGION | D98: 172715 | E98: BFINAG02 | F98: ECOLOGIA | G98: DAMARIS PERDOMO MEDINA | H98: CATEDRA VISITANTE DOCENTE | I98: 44886 | J98: 44887 | K98: UNIVERSIDAD SURCOLOMBIANA (PITALITO)-RESERVA DE LA SOCIEDAD CIVIL EL ENCANTO PALESTINA HUILA-PITALITO | L98: 2 | M98: 18 | O98: Alberto Mora | P98: 150000 | Q98: 41000 | R98: 10000 | U98: 150000 | V98: =L98*U98 -> 300000
A99: PITALITO | B99: INGENIERÍA AGRÍCOLA | C99: DESARROLLO SOSTENIBLE EN EL SECTOR AGROPECUARIO EN PRO DE LA CONSERVACION DEL MEDIO AMBIENTE | D99: 173486 | E99: FEINAG64 | F99: DESARROLLO SOSTENIBLE Y MEDIO AMBIENTE | G99: INGRID CONSTANZA OSORIO OVIEDO | H99: CATEDRA VISITANTE DOCENTE | I99: 44887 | J99: 44889 | K99: SEDE USCO PITALITO-RESTREPO(META): FINCA AGROECOLOGICA LA COSMOPOLITANA, BIOPARQUE LOS OCARROS-PITALITO | L99: 3 | M99: 8 | N99: NO TIENE FORMATO MI-FOR-FO-16 | T99: 9600000 | U99: 150000 | V99: =L99*U99 -> 450000
A100: PITALITO | B100: INGENIERÍA AGRÍCOLA | C100: VISITA DA LAS INSTALACIONES DE DISTRITOS DE RIEGO EN EL DEPARTAMENTO DEL HUILA, CUNDINAMARCA Y BOYACA (HUILA:OVEJERAS Y USOIGUA EN CAMPOALEGRE, JUNCAL EN PALERMO) Y (BOYACA; DISTRITO DE RIEGO DEL ALTO CHICAMOCHA Y FIRAVITOBA DESDE TUNJA HASTA SOGAMOSO) | D100: 172823 | E100: BEINAG18 | F100: INGENIERIA DE RIEGOS II | G100: JHON JAIRO BELTRAN DIAZ | H100: NOMBRAMIENTO OCASIONAL DOCENTE | I100: 44889 | J100: 44892 | K100: PITALITO- GARZON-CAMPOALEGRE-HOBO-BETANIA-JUNCAL-NEIVA-TUNJA-DUITAMA-SOGAMOSOS-NEIVA-PITALITO | L100: 4 | M100: 6 | N100: NO TIENE FORMATO MI-FOR-FO-16 | O100: Desiderio Olarte | P100: 450000 | Q100: 320000 | R100: 60000 | U100: 150000 | V100: =L100*U100 -> 600000
...
